helipypter/__init__.py
helipypter/classes.py
helipypter/funcs.py
helipypter/vehicles.py
tests/__init__.py
tests/doctest.py
tests/project_test.py
heliPypter-0.0.7.dist-info/LICENSE
heliPypter-0.0.7.dist-info/METADATA
heliPypter-0.0.7.dist-info/WHEEL
heliPypter-0.0.7.dist-info/top_level.txt
heliPypter-0.0.7.dist-info/RECORD
