Metadata-Version: 2.1
Name: heliPypter
Version: 0.0.7
Summary: A package for rotorcraft performance evaluation.
Home-page: https://github.com/czarified/helipypter
Author: Benjamin Crews
Author-email: aceF22@gmail.com
License: UNKNOWN
Platform: UNKNOWN
Classifier: Programming Language :: Python :: 3
Classifier: License :: OSI Approved :: GNU General Public License v3 (GPLv3)
Classifier: Operating System :: OS Independent
Requires-Python: >=3.6
